{"cancion":"te-quiero-igual","banda":"andres-calamaro","acordes":{"partes":[{"nombre":"parte1","acordes":["G","D","Em"]},{"nombre":"parte2","acordes":["C"]},{"nombre":"parte3","acordes":["G"]},{"nombre":"parte4","acordes":["D"]}],"orden_partes":[0,1,0,1,0,1,2,3,0,1,0,1,0,1,2,3,0,1,0,1,0,1,2,3,1,2,1,2,1,2,3,1,2,1,2,1,2,3,0,1,0,1,0,1,2,3,2,3,1,0,1,0,1,0,1,2,3]},"escala":"G","letras":[["e quiero pero te"," llevaste la flo","r y me dejast","e el florero/nTe qui"],["ero me deja","ste la ceniz","a y te llevast","e el cenicero/nTe qui"],["ero pero te"," llevaste marzo ","y te rendiste ","en febrero/nPrim"],["ero te qu","iero igual/nT"],["e quiero , te lle","vaste la cabeza"," y me dejast","e el sombrero/nTe quiero"],[" pero te"," olvidaste ab","ril en el ropero"," pero igual/nTe quiero"],["  no me gu","sta esper","ar pero igual ","te espero/nPrim"],["ero te qui","ero igual/nT"],["e quiero me deja","ste el florero"," y te llevaste ","la flor pero igual/nTe quiero"],[". me deja","ste el vestid","o y te llevast","e el amor/nTe qu"],["iero pero te"," olvidaste abril"," en el ropero","/nPrim"],["ero te qui","ero igual/nN"],["o s"," si ","estoy des","pierto o tengo l","os ojos a","biertos","/nN"],["o s"," si ","estoy des","pierto o tengo l","os ojos a","biertos","/nTe qu"],["iero, no sé s","i estoy despierto"," o tengo los oj","os abiertos/nS"],["é que t","e quiero y que me esp","eran má","s aeropuertos/nTe qu"],["iero te lle","vaste la vela ","y me dejast","e el entierro/nPrim"],["ero te qui","ero igual/n[T"],["erce","ira ","Parte]/nT"],["e quiero pero te"," llevaste la flo","r y me dejast","e el florero/nTe quiero"],[" me deja","ste la ceniza"," y te llevast","e el cenicero/nTe quiero"],[" pero te"," llevaste mar","zo y te rendist","e en febrero/nPri"],["mero te qui","ero igual/n"],[],["","","","","","","","","","","","","","","","","","","","","","","","","","","","","","","","","","","","","","","","","","","","","","","","","","","","","","","","","","","","","","","","","","","","","","","","","","","","","","","","","","","","","","",""]],"bpm":"128","calidad":0,"compas_cantidad":4,"compas_unidad":4}