{"cancion": "amor-ate-o-fim", "banda": "gilberto-gil", "escala": "Em5-/7", "tempo": 60, "compas_cantidad": 4, "compas_unidad": 4, "acordes": {"partes": [{"nombre": "parte1", "acordes": ["Em5-/7", "A5+/7", "D7/9", "Dm5-/7", "G7/13", "C7+/9", "F7/13", "F5+/7", "Bb7+", "D7/9", "C/D", "G7/13", "Bb/C", "C7/9", "F7/13", "Em5-/7", "A5+/7", "D7/9", "Dm5-/7", "G7/13", "C7+/9", "F7/13", "F5+/7", "Bb7+", "D7/9", "C/D", "G7/13", "Bb/C", "C7/9", "F7/13", "Bb7+", "D7", "Gm", "D7", "Gm", "A7", "Dm", "A7", "Dm", "D7", "Gm7", "Cm7", "F7", "Bb7+", "Em5-/7", "A5+/7", "Dm", "Dm/C", "Bb7+", "G/A", "Gm7", "Fm7", "Em5-/7", "A5+/7", "D7/9", "Dm7/9", "G7/13", "Em5-/7", "A5+/7", "Dm7/9", "G7/13", "Em5-/7", "Dm7/9", "G7/13", "Em5-/7", "A5+/7", "Dm7/9", "G7/13", "C7+/9"]}], "orden_partes": [0]}, "letras": [["Amor n\u00e3o ", "tem se acab", "ar/n"], ["Eu quero e se", "i que vo", "u ficar ", " ", "/n"], ["At\u00e9 o fim eu vo", "u te amar /n"], ["At\u00e9 que a vida em mim re", "solva se apagar", "", "", "/n"], ["Amor n\u00e3o ", "tem se acaba", "r/n"], ["Eu quero e s", "ei que vo", "u ficar ", " ", "/n"], ["At\u00e9 o fim eu vou te amar", " /n"], ["At\u00e9 que a vida em mim re", "solva se apa.....", ".....g", "ar", "", "/n"], ["O am", "or \u00e9 como uma ", "rosa num jardim", "/nA gente c"], ["uida, a gente", " olha/nA gente dei"], ["xa o sol ba", "ter/nPra crescer"], [", pra crescer ", "/nA rosa do "], ["amor tem se", "mpre que crescer", "/n"], ["A rosa do amo", "r n\u00e3o vai despe", "talar/n"], ["Pra quem cuida b", "em da rosa/n"], ["Pra quem sabe cultiv", "ar", "/n"], ["Amor n\u00e3o t", "em que se acaba", "r/n"], ["At\u00e9 o fim ", "da minha vida eu vo", "u te amar", "/n"], ["Eu sei que o amor ", "n\u00e3o tem que se ", "apagar/n"], ["At\u00e9 o fim da minh", "a vida eu ", "vou te am", "ar/n"], ["Eu sei que o amor n\u00e3o", " tem que se apagar.", ""]], "bpm": 80, "etiquetas": [], "medias": [{"tipo": "Youtube", "id": "p38aG1JT9yQ", "delay": 0}]}