{
    "cancion": "Sobran-las-palabras",
    "banda": "jose-larralde",
    "escala": "Am",
    "tempo": 60,
    "compas_cantidad": 4,
    "compas_unidad": 4,
    "acordes": {
        "partes": [
            {
                "nombre": "parte1",
                "acordes": [
                    "Am",
                    "Dm",
                    "G7",
                    "C",
                    "E",
                    "Am",
                    "Am",
                    "Dm",
                    "E",
                    "Am",
                    "Dm",
                    "E",
                    "Am",
                    "G7",
                    "C",
                    "Dm",
                    "E",
                    "Am",
                    "G7",
                    "F",
                    "E",
                    "Am",
                    "G7",
                    "F",
                    "E",
                    "Am",
                    "Am",
                    "Dm",
                    "E",
                    "Am",
                    "Dm",
                    "E",
                    "Am",
                    "G7",
                    "C",
                    "Dm",
                    "E",
                    "Am",
                    "G7",
                    "F",
                    "E",
                    "Am",
                    "G7",
                    "F",
                    "E",
                    "Am",
                    "Dm",
                    "E",
                    "Am",
                    "Dm",
                    "E",
                    "Am",
                    "G7",
                    "C",
                    "E",
                    "Am",
                    "Am",
                    "G7",
                    "F",
                    "E(2)",
                    "Am",
                    "G7",
                    "F",
                    "E",
                    "Am",
                    "Dm",
                    "E",
                    "Am",
                    "Dm",
                    "F",
                    "E",
                    "Am",
                    "Dm",
                    "G7",
                    "C"
                ]
            }
        ],
        "orden_partes": [
            0
        ]
    },
    "letras": [
        [],
        [
            "  Aprendí a bus",
            "carte, nada más, sin saber que e",
            "stabas,/n"
        ],
        [
            "  tan adentro m",
            "o y más allá... de todo y d",
            "e nada./n"
        ],
        [
            "  Aprendí a llo",
            "rarte y sin saber, que en cada ma",
            "ana/nbajabas el s"
        ],
        [
            "ol para traer... luces de espera",
            "nza./n"
        ],
        [
            "  Qué extraño fue ",
            "todo, ya lo ves.",
            ".. la vida que pa",
            "sa,/n"
        ],
        [
            "  y en la masa aust",
            "era, desnudez...",
            " sobran las palabr",
            "as./n"
        ],
        [
            "  Sobran las palabras.../n"
        ],
        [
            "  Que argumento gr",
            "is tiene el perfil, de las horas lac",
            "ias,/n"
        ],
        [
            "deslozando l",
            "grimas de 'actriz', de estérile",
            "s páginas./n"
        ],
        [
            "  Anda suelto el ai",
            "re en el pinar... borrando nostal",
            "gias,/nqué extraño fue"
        ],
        [
            " todo; pa' qué llorar... si hoy se que m",
            "e amas./n"
        ],
        [
            "  Qué extraño fue ",
            "todo, ya lo ves.",
            ".. la vida que pa",
            "sa,/n"
        ],
        [
            "  y en la masa auste",
            "ra, desnudez...",
            " sobran las palab",
            "ras./n"
        ],
        [
            "  Sobran las palabras.../nAprendí a bus"
        ],
        [
            "carte, nada más",
            "... sin saber que est",
            "abas.../ntan adentro m"
        ],
        [
            "ío y más allá... de todo y de",
            " nada./n"
        ],
        [
            "  Aprendí a llor",
            "arte, sin saber... que en cada ma",
            "ana.../nbajabas el s"
        ],
        [
            "ol para traer... luces de espera",
            "nza./n"
        ],
        [
            "  Qué extraño fue ",
            "todo, ya lo vez.",
            ".. la vida que pa",
            "sa,/n"
        ],
        [
            "  y en la masa auste",
            "ra, desnudez...",
            " sobran las palab",
            "ras./n"
        ],
        [
            "  Sobran las palabras...",
            "",
            "",
            "",
            "/n"
        ],
        []
    ],
    "bpm": 80,
    "etiquetas": []
}