{
    "cancion": "O-Tolo",
    "banda": "roberto-carlos",
    "escala": "D",
    "tempo": 60,
    "compas_cantidad": 4,
    "compas_unidad": 4,
    "acordes": {
        "partes": [
            {
                "nombre": "parte1",
                "acordes": [
                    "D",
                    "Bm7",
                    "Em7"
                ]
            },
            {
                "nombre": "parte2",
                "acordes": [
                    "A7/9",
                    "D",
                    "A7/9",
                    "D",
                    "Bm7",
                    "Em7",
                    "A7/9"
                ]
            },
            {
                "nombre": "parte3",
                "acordes": [
                    "A7/9",
                    "C#m7(b5)",
                    "F#7",
                    "Bm7",
                    "Am7"
                ]
            },
            {
                "nombre": "parte4",
                "acordes": [
                    "D7",
                    "G7+",
                    "G#°",
                    "D/A",
                    "B7",
                    "Em7",
                    "A7/9",
                    "D"
                ]
            },
            {
                "nombre": "parte5",
                "acordes": [
                    "A7/9",
                    "D",
                    "Bm7",
                    "Em7",
                    "B7"
                ]
            }
        ],
        "orden_partes": [
            0,
            1,
            0,
            2,
            3,
            4,
            2,
            3
        ]
    },
    "letras": [
        [],
        [
            "   Como um tolo/nFui seg"
        ],
        [
            "uindo o seu cam",
            "inho/nMe dei"
        ],
        [
            "xando ser levado/nPor suas m"
        ],
        [
            "ãos",
            "/nNa ilusão do a"
        ],
        [
            "mor/nSem pen"
        ],
        [
            "sar na dor/n"
        ],
        [
            "   Eu me esqueci/nDe me resguar"
        ],
        [
            "dar/n"
        ],
        [
            "   De pensar em mim/nNa velocidade em que eu "
        ],
        [
            "vinha/n"
        ],
        [
            "   Não pude mais parar/n"
        ],
        [
            "   E até os sinais",
            "/nQue os a"
        ],
        [
            "migos deram/n"
        ],
        [
            "Eu não percebi",
            "",
            "/n"
        ],
        [
            "Tudo ultrapassei/n"
        ],
        [
            "Nada respeitei/n"
        ],
        [
            "Eu só vi você",
            "/n"
        ],
        [
            "   Quanta insensatez/n"
        ],
        [
            "   Quanta estupidez/n"
        ],
        [
            "   O que eu fiz pra mim",
            "/n"
        ],
        [
            "Como um bêbado/nBebi suas pal"
        ],
        [
            "avras/n"
        ],
        [
            "   E quando eu acordei",
            "/n"
        ],
        [
            "   E te procurei/nNem sequer me achei"
        ],
        [],
        [],
        [],
        [],
        [],
        [],
        []
    ],
    "bpm": 80,
    "etiquetas": []
}